{
  "version": 1,
  "meta": {
    "generated_at": "2026-07-06T08:54:40.317572+08:00",
    "trade_date": "2026-07-06",
    "batch": "now",
    "data_status": "ok",
    "disclaimer": "仅供研究参考，不构成投资建议。"
  },
  "themes": [
    {
      "name": "贵金属",
      "summary": "贵金属 主题因市场强度和触发信号进入早盘观察。",
      "score": 101.84,
      "signals": [
        "隔夜信号：隔夜 GLD +2.03%，映射：贵金属",
        "隔夜信号：夜盘 COMEX黄金 +1.81%，映射：贵金属",
        "A股概念板块涨跌幅 6.17%，上涨家数 13"
      ],
      "evidence": [
        {
          "kind": "overnight",
          "text": "隔夜 GLD +2.03%，映射：贵金属",
          "source_name": "overnight",
          "url": "https://finnhub.io/docs/api/quote",
          "observed_at": null
        },
        {
          "kind": "overnight",
          "text": "夜盘 COMEX黄金 +1.81%，映射：贵金属",
          "source_name": "overnight",
          "url": "https://finance.sina.com.cn/money/future/hf.html",
          "observed_at": null
        },
        {
          "kind": "market",
          "text": "贵金属 成交额 40180000000",
          "source_name": "akshare:stock_board_industry_summary_ths",
          "url": "",
          "observed_at": null
        }
      ],
      "risks": [
        "主题热度可能在开盘后快速变化"
      ]
    },
    {
      "name": "军工装备",
      "summary": "军工装备 主题因市场强度和触发信号进入早盘观察。",
      "score": 88.46,
      "signals": [
        "A股概念板块涨跌幅 4.42%，上涨家数 77"
      ],
      "evidence": [
        {
          "kind": "market",
          "text": "军工装备 成交额 59937000000",
          "source_name": "akshare:stock_board_industry_summary_ths",
          "url": "",
          "observed_at": null
        }
      ],
      "risks": [
        "主题热度可能在开盘后快速变化"
      ]
    },
    {
      "name": "自动化设备",
      "summary": "自动化设备 主题因市场强度和触发信号进入早盘观察。",
      "score": 82.24,
      "signals": [
        "A股概念板块涨跌幅 3.83%，上涨家数 72"
      ],
      "evidence": [
        {
          "kind": "market",
          "text": "自动化设备 成交额 91803000000",
          "source_name": "akshare:stock_board_industry_summary_ths",
          "url": "",
          "observed_at": null
        }
      ],
      "risks": [
        "主题热度可能在开盘后快速变化"
      ]
    },
    {
      "name": "电机",
      "summary": "电机 主题因市场强度和触发信号进入早盘观察。",
      "score": 81.92,
      "signals": [
        "A股概念板块涨跌幅 5.59%，上涨家数 24"
      ],
      "evidence": [
        {
          "kind": "market",
          "text": "电机 成交额 13047000000",
          "source_name": "akshare:stock_board_industry_summary_ths",
          "url": "",
          "observed_at": null
        }
      ],
      "risks": [
        "主题热度可能在开盘后快速变化"
      ]
    },
    {
      "name": "消费电子",
      "summary": "消费电子 主题因市场强度和触发信号进入早盘观察。",
      "score": 81.0,
      "signals": [
        "隔夜信号：隔夜 AAPL +4.84%，映射：消费电子 苹果概念",
        "A股概念板块涨跌幅 2.39%，上涨家数 74"
      ],
      "evidence": [
        {
          "kind": "overnight",
          "text": "隔夜 AAPL +4.84%，映射：消费电子 苹果概念",
          "source_name": "overnight",
          "url": "https://finnhub.io/docs/api/quote",
          "observed_at": null
        },
        {
          "kind": "market",
          "text": "消费电子 成交额 97261000000",
          "source_name": "akshare:stock_board_industry_summary_ths",
          "url": "",
          "observed_at": null
        }
      ],
      "risks": [
        "主题热度可能在开盘后快速变化"
      ]
    }
  ],
  "candidates": [
    {
      "code": "688017",
      "name": "绿的谐波",
      "market": "科创板",
      "themes": [
        "自动化设备"
      ],
      "score": 131.45,
      "reason": "绿的谐波 与 自动化设备 主题相关，且交易活跃度进入候选池。",
      "evidence": [
        {
          "kind": "theme",
          "text": "进入 自动化设备 主题产业链候选",
          "source_name": "",
          "url": "",
          "observed_at": null
        },
        {
          "kind": "market",
          "text": "成交额 12529366533，涨跌幅 18.15%",
          "source_name": "",
          "url": "",
          "observed_at": null
        },
        {
          "kind": "activity",
          "text": "换手率 0.00%，量比 0.00",
          "source_name": "",
          "url": "",
          "observed_at": null
        }
      ],
      "risks": [
        {
          "kind": "theme",
          "text": "自动化设备 热度可能在开盘后快速回落"
        },
        {
          "kind": "volatility",
          "text": "近期涨幅较高，盘中波动可能放大"
        }
      ],
      "snapshot": {
        "pct_change": 18.146,
        "amount": 12529366533.0,
        "turnover_rate": 0.0,
        "volume_ratio": 0.0
      }
    },
    {
      "code": "301199",
      "name": "迈赫股份",
      "market": "创业板",
      "themes": [
        "自动化设备"
      ],
      "score": 130.34,
      "reason": "迈赫股份 与 自动化设备 主题相关，且交易活跃度进入候选池。",
      "evidence": [
        {
          "kind": "theme",
          "text": "进入 自动化设备 主题产业链候选",
          "source_name": "",
          "url": "",
          "observed_at": null
        },
        {
          "kind": "market",
          "text": "成交额 207344828，涨跌幅 20.02%",
          "source_name": "",
          "url": "",
          "observed_at": null
        },
        {
          "kind": "activity",
          "text": "换手率 0.00%，量比 0.00",
          "source_name": "",
          "url": "",
          "observed_at": null
        }
      ],
      "risks": [
        {
          "kind": "theme",
          "text": "自动化设备 热度可能在开盘后快速回落"
        },
        {
          "kind": "volatility",
          "text": "近期涨幅较高，盘中波动可能放大"
        }
      ],
      "snapshot": {
        "pct_change": 20.023,
        "amount": 207344828.0,
        "turnover_rate": 0.0,
        "volume_ratio": 0.0
      }
    },
    {
      "code": "688523",
      "name": "航天环宇",
      "market": "科创板",
      "themes": [
        "军工装备"
      ],
      "score": 123.98,
      "reason": "航天环宇 与 军工装备 主题相关，且交易活跃度进入候选池。",
      "evidence": [
        {
          "kind": "theme",
          "text": "进入 军工装备 主题产业链候选",
          "source_name": "",
          "url": "",
          "observed_at": null
        },
        {
          "kind": "market",
          "text": "成交额 738317333，涨跌幅 16.23%",
          "source_name": "",
          "url": "",
          "observed_at": null
        },
        {
          "kind": "activity",
          "text": "换手率 0.00%，量比 0.00",
          "source_name": "",
          "url": "",
          "observed_at": null
        }
      ],
      "risks": [
        {
          "kind": "theme",
          "text": "军工装备 热度可能在开盘后快速回落"
        },
        {
          "kind": "volatility",
          "text": "近期涨幅较高，盘中波动可能放大"
        }
      ],
      "snapshot": {
        "pct_change": 16.232,
        "amount": 738317333.0,
        "turnover_rate": 0.0,
        "volume_ratio": 0.0
      }
    },
    {
      "code": "301051",
      "name": "信濠光电",
      "market": "创业板",
      "themes": [
        "消费电子"
      ],
      "score": 123.25,
      "reason": "信濠光电 与 消费电子 主题相关，且交易活跃度进入候选池。",
      "evidence": [
        {
          "kind": "theme",
          "text": "进入 消费电子 主题产业链候选",
          "source_name": "",
          "url": "",
          "observed_at": null
        },
        {
          "kind": "market",
          "text": "成交额 791015695，涨跌幅 17.07%",
          "source_name": "",
          "url": "",
          "observed_at": null
        },
        {
          "kind": "activity",
          "text": "换手率 0.00%，量比 0.00",
          "source_name": "",
          "url": "",
          "observed_at": null
        }
      ],
      "risks": [
        {
          "kind": "theme",
          "text": "消费电子 热度可能在开盘后快速回落"
        },
        {
          "kind": "volatility",
          "text": "近期涨幅较高，盘中波动可能放大"
        }
      ],
      "snapshot": {
        "pct_change": 17.069,
        "amount": 791015695.0,
        "turnover_rate": 0.0,
        "volume_ratio": 0.0
      }
    },
    {
      "code": "300139",
      "name": "晓程科技",
      "market": "创业板",
      "themes": [
        "贵金属"
      ],
      "score": 122.37,
      "reason": "晓程科技 与 贵金属 主题相关，且交易活跃度进入候选池。",
      "evidence": [
        {
          "kind": "theme",
          "text": "进入 贵金属 主题产业链候选",
          "source_name": "",
          "url": "",
          "observed_at": null
        },
        {
          "kind": "market",
          "text": "成交额 3088254312，涨跌幅 12.86%",
          "source_name": "",
          "url": "",
          "observed_at": null
        },
        {
          "kind": "activity",
          "text": "换手率 0.00%，量比 0.00",
          "source_name": "",
          "url": "",
          "observed_at": null
        }
      ],
      "risks": [
        {
          "kind": "theme",
          "text": "贵金属 热度可能在开盘后快速回落"
        },
        {
          "kind": "volatility",
          "text": "近期涨幅较高，盘中波动可能放大"
        }
      ],
      "snapshot": {
        "pct_change": 12.862,
        "amount": 3088254312.0,
        "turnover_rate": 0.0,
        "volume_ratio": 0.0
      }
    },
    {
      "code": "300777",
      "name": "中简科技",
      "market": "创业板",
      "themes": [
        "军工装备"
      ],
      "score": 119.42,
      "reason": "中简科技 与 军工装备 主题相关，且交易活跃度进入候选池。",
      "evidence": [
        {
          "kind": "theme",
          "text": "进入 军工装备 主题产业链候选",
          "source_name": "",
          "url": "",
          "observed_at": null
        },
        {
          "kind": "market",
          "text": "成交额 1073896325，涨跌幅 14.50%",
          "source_name": "",
          "url": "",
          "observed_at": null
        },
        {
          "kind": "activity",
          "text": "换手率 0.00%，量比 0.00",
          "source_name": "",
          "url": "",
          "observed_at": null
        }
      ],
      "risks": [
        {
          "kind": "theme",
          "text": "军工装备 热度可能在开盘后快速回落"
        },
        {
          "kind": "volatility",
          "text": "近期涨幅较高，盘中波动可能放大"
        }
      ],
      "snapshot": {
        "pct_change": 14.497,
        "amount": 1073896325.0,
        "turnover_rate": 0.0,
        "volume_ratio": 0.0
      }
    },
    {
      "code": "300660",
      "name": "江苏雷利",
      "market": "创业板",
      "themes": [
        "电机"
      ],
      "score": 116.49,
      "reason": "江苏雷利 与 电机 主题相关，且交易活跃度进入候选池。",
      "evidence": [
        {
          "kind": "theme",
          "text": "进入 电机 主题产业链候选",
          "source_name": "",
          "url": "",
          "observed_at": null
        },
        {
          "kind": "market",
          "text": "成交额 1374143901，涨跌幅 14.36%",
          "source_name": "",
          "url": "",
          "observed_at": null
        },
        {
          "kind": "activity",
          "text": "换手率 0.00%，量比 0.00",
          "source_name": "",
          "url": "",
          "observed_at": null
        }
      ],
      "risks": [
        {
          "kind": "theme",
          "text": "电机 热度可能在开盘后快速回落"
        },
        {
          "kind": "volatility",
          "text": "近期涨幅较高，盘中波动可能放大"
        }
      ],
      "snapshot": {
        "pct_change": 14.359,
        "amount": 1374143901.0,
        "turnover_rate": 0.0,
        "volume_ratio": 0.0
      }
    },
    {
      "code": "300607",
      "name": "拓斯达",
      "market": "创业板",
      "themes": [
        "自动化设备"
      ],
      "score": 116.31,
      "reason": "拓斯达 与 自动化设备 主题相关，且交易活跃度进入候选池。",
      "evidence": [
        {
          "kind": "theme",
          "text": "进入 自动化设备 主题产业链候选",
          "source_name": "",
          "url": "",
          "observed_at": null
        },
        {
          "kind": "market",
          "text": "成交额 4594583902，涨跌幅 13.55%",
          "source_name": "",
          "url": "",
          "observed_at": null
        },
        {
          "kind": "activity",
          "text": "换手率 0.00%，量比 0.00",
          "source_name": "",
          "url": "",
          "observed_at": null
        }
      ],
      "risks": [
        {
          "kind": "theme",
          "text": "自动化设备 热度可能在开盘后快速回落"
        },
        {
          "kind": "volatility",
          "text": "近期涨幅较高，盘中波动可能放大"
        }
      ],
      "snapshot": {
        "pct_change": 13.551,
        "amount": 4594583902.0,
        "turnover_rate": 0.0,
        "volume_ratio": 0.0
      }
    },
    {
      "code": "000975",
      "name": "山金国际",
      "market": "深市主板",
      "themes": [
        "贵金属"
      ],
      "score": 112.25,
      "reason": "山金国际 与 贵金属 主题相关，且交易活跃度进入候选池。",
      "evidence": [
        {
          "kind": "theme",
          "text": "进入 贵金属 主题产业链候选",
          "source_name": "",
          "url": "",
          "observed_at": null
        },
        {
          "kind": "market",
          "text": "成交额 1322045073，涨跌幅 9.98%",
          "source_name": "",
          "url": "",
          "observed_at": null
        },
        {
          "kind": "activity",
          "text": "换手率 0.00%，量比 0.00",
          "source_name": "",
          "url": "",
          "observed_at": null
        }
      ],
      "risks": [
        {
          "kind": "theme",
          "text": "贵金属 热度可能在开盘后快速回落"
        },
        {
          "kind": "volatility",
          "text": "近期涨幅较高，盘中波动可能放大"
        }
      ],
      "snapshot": {
        "pct_change": 9.978,
        "amount": 1322045073.0,
        "turnover_rate": 0.0,
        "volume_ratio": 0.0
      }
    },
    {
      "code": "600988",
      "name": "赤峰黄金",
      "market": "沪市主板",
      "themes": [
        "贵金属"
      ],
      "score": 112.08,
      "reason": "赤峰黄金 与 贵金属 主题相关，且交易活跃度进入候选池。",
      "evidence": [
        {
          "kind": "theme",
          "text": "进入 贵金属 主题产业链候选",
          "source_name": "",
          "url": "",
          "observed_at": null
        },
        {
          "kind": "market",
          "text": "成交额 1152376459，涨跌幅 10.00%",
          "source_name": "",
          "url": "",
          "observed_at": null
        },
        {
          "kind": "activity",
          "text": "换手率 0.00%，量比 0.00",
          "source_name": "",
          "url": "",
          "observed_at": null
        }
      ],
      "risks": [
        {
          "kind": "theme",
          "text": "贵金属 热度可能在开盘后快速回落"
        },
        {
          "kind": "volatility",
          "text": "近期涨幅较高，盘中波动可能放大"
        }
      ],
      "snapshot": {
        "pct_change": 10.004,
        "amount": 1152376459.0,
        "turnover_rate": 0.0,
        "volume_ratio": 0.0
      }
    }
  ],
  "warnings": []
}
